Workbook

Sheet Summary
A2: ='data-sheet'!A6 | B2: ='data-sheet'!N4
A3: ='data-sheet'!A7 | B3: ='data-sheet'!D7 | C3: ='data-sheet'!E7 | D3: ='data-sheet'!F7 | E3: ='data-sheet'!J7 | G3: ='data-sheet'!K7 | H3: ='data-sheet'!L3 | I3: ='data-sheet'!M7 | J3: ='data-sheet'!N7 | K3: ='data-sheet'!O7 | L3: ='data-sheet'!P7
A4: ='data-sheet'!A8 | B4: ='data-sheet'!D8 | C4: ='data-sheet'!E8 | D4: ='data-sheet'!F8 | E4: ='data-sheet'!J8 | G4: ='data-sheet'!K8 | H4: ='data-sheet'!L8 | I4: ='data-sheet'!M8 | J4: ='data-sheet'!N8 | K4: ='data-sheet'!O8 | L4: ='data-sheet'!P8
L5: Approval Required
A6: ='data-sheet'!A11
B7: ='data-sheet'!D12 | C7: ='data-sheet'!E12 | D7: ='data-sheet'!F12 | E7: ='data-sheet'!J12 | F7: Pro-rated PO Value as per surveyed length | G7: ='data-sheet'!K12 | H7: =H3 | I7: ='data-sheet'!M12 | J7: ='data-sheet'!N12
A8: ='data-sheet'!A14 | B8: ='data-sheet'!D14 | C8: ='data-sheet'!E14 | D8: ='data-sheet'!F14 | E8: ='data-sheet'!J14 | G8: ='data-sheet'!K14 | H8: ='data-sheet'!L14 | I8: ='data-sheet'!M14 | J8: ='data-sheet'!N14
A9: ='data-sheet'!A15 | B9: ='data-sheet'!D15 | C9: ='data-sheet'!E15 | D9: ='data-sheet'!F15 | E9: ='data-sheet'!J15 | G9: ='data-sheet'!K15 | H9: ='data-sheet'!L15 | I9: ='data-sheet'!M15 | J9: ='data-sheet'!N15
A10: ='data-sheet'!A16 | B10: ='data-sheet'!D16 | C10: ='data-sheet'!E16 | D10: ='data-sheet'!F16 | E10: ='data-sheet'!J16 | F10: ='data-sheet'!K16 | G10: =G9 | I10: ='data-sheet'!M16 | J10: ='data-sheet'!N16

Sheet data-sheet
A2: Budget
A3: SR No. | B3: Route No. | C3: Type Modility | D3: PO Length | E3: Surveyed length | F3: Budgeted RI Cost W/O Deposit | G3: Budgeted RI/mtr Cost | H3: Budgeted Service/mtr Cost | I3: Budgeted Material/mtr Cost | J3: Total/mtr Cost | L3: Total Budgeted Cost for route | M3: Target Date of comletion | N3: Category Type | O3: PO Number | P3: PO Value W/O GST | Q3: PO Value/mtr
A4: 1 | G4: =F4/E4 | J4: =G4+H4+I4 | L4: =J4*E4 | Q4: =P4/D4
A6: Total DN Analysis
A7: Total Cumulative DN Received | D7: DN Length | E7: Surveyed length | F7: Total Actual RI Including All Non-Refundable Charges (Excluding Deposit) | G7: Actual RI/mtr Cost | H7: Actual Service/mtr Cost | I7: Actual Material/mtr Cost | J7: Total/mtr Cost | K7: Total Actual Cost for route | L7: Total Budgeted Cost for route | M7: Difference Total | N7: Difference/mtr Cost | O7: Deposit Amount | P7: Total Payable Amount to Authority
A8: =SUBTOTAL(3,#REF!,B21,#REF!,#REF!,#REF!,#REF!,#REF!,#REF!,#REF!,#REF!,#REF!,#REF!,#REF!,#REF!,#REF!,#REF!,#REF!,#REF!,#REF!) | D8: =SUM(D21,#REF!,#REF!,#REF!,#REF!,#REF!,#REF!,#REF!,#REF!,#REF!,#REF!,#REF!,#REF!,#REF!,#REF!,#REF!,#REF!,#REF!,#REF!) | E8: =SUM(E21,#REF!,#REF!,#REF!,#REF!,#REF!,#REF!,#REF!,#REF!,#REF!,#REF!,#REF!,#REF!,#REF!,#REF!,#REF!,#REF!,#REF!,#REF!) | F8: =SUM(F21,#REF!,#REF!,#REF!,#REF!,#REF!,#REF!,#REF!,#REF!,#REF!,#REF!,#REF!,#REF!,#REF!,#REF!,#REF!,#REF!,#REF!,#REF!) | G8: =F8/D8 | H8: =(H21*$D21+#REF!*#REF!+#REF!*#REF!+#REF!*#REF!+#REF!*#REF!+#REF!*#REF!+#REF!*#REF!+#REF!*#REF!+#REF!*#REF!+#REF!*#REF!+#REF!*#REF!+#REF!*#REF!+#REF!*#REF!+#REF!*#REF!+#REF!*#REF!+#REF!*#REF!+#REF!*#REF!+#REF!*#REF!)/$D8 | I8: =(I21*$D21+#REF!*#REF!+#REF!*#REF!+#REF!*#REF!+#REF!*#REF!+#REF!*#REF!+#REF!*#REF!+#REF!*#REF!+#REF!*#REF!+#REF!*#REF!+#REF!*#REF!+#REF!*#REF!+#REF!*#REF!+#REF!*#REF!+#REF!*#REF!+#REF!*#REF!+#REF!*#REF!+#REF!*#REF!+#REF!*#REF!)/$D8 | J8: =G8+H8+I8 | K8: =J8*D8 | L8: =L$4/E$4*D8 | M8: =(J$4*D8)-K8 | N8: =M8/D8 | O8: =SUM(O21+#REF!+#REF!+#REF!+#REF!+#REF!+#REF!+#REF!+#REF!+#REF!+#REF!+#REF!+#REF!+#REF!+#REF!+#REF!+#REF!+#REF!) | P8: =F8+O8
A11: Projection
D12: PO Length | E12: Surveyed length | F12: Balance Budgeted RI Cost W/O Deposit | G12: Budgeted RI/mtr Cost | H12: Projected Service/mtr Cost | I12: Projected Material/mtr Cost | J12: Total/mtr Cost | K12: Total Actual Cost for route | L12: Total Budgeted Cost for route | M12: Estimated Difference | N12: Difference/mtr Cost
A14: Balance Route | E14: =E4-E8 | F14: =G14*E14 | G14: =G4 | H14: =H4 | I14: =I4 | J14: =G14+H14+I14 | K14: =J14*E14 | L14: =L$4/E$4*E14
A15: Total Route | D15: =D4 | E15: =E4 | F15: =F8+F14 | G15: =(G8*$E8+G14*$E14)/$E15 | H15: =(H8*$E8+H14*$E14)/$E15 | I15: =(I8*$E8+I14*$E14)/$E15 | J15: =SUM(G15:I15) | K15: =J15*E15 | L15: =L$4/E$4*E15 | M15: =L4-K15 | N15: =M15/E15
A16: Comparison with PO | E16: =E15 | J16: =Q4 | K16: =J16*E16 | L16: =L15 | M16: =K16-K15 | N16: =M16/E15
A19: Demand Note Details
A20: Approval Required | B20: DN Details | C20: Subsection ID | D20: DN Length | E20: Surveyed length | F20: Total Actual RI Including all Non-Refundable Charges (W/O Deposit) | G20: Actual RI/mtr Cost | H20: Actual Service/mtr Cost | I20: Actual Material/mtr Cost | J20: Total/mtr Cost | K20: Total Actual Cost for route | L20: Total Budgeted Cost for route | M20: Difference Total | N20: Difference/Cost | O20: Deposit Amount | P20: Total Payble Amount to Authority
A21: 1 | D21: =SUM(H23:H24) | F21: =SUM(F23:F26) | G21: =F21/D21 | J21: =G21+H21+I21 | K21: =J21*D21 | L21: =L$4/E$4*D21 | M21: =(J$4*D21)-K21 | N21: =M21/D21 | O21: =F23/2 | P21: =F21+O21
E22: Breakup | G22: Particulars | H22: Length | I22: Rate | J22: DLP | K22: Total
E23: RI Charges | F23: =K26 | K23: =H23*I23*J23
E24: Ground Rent | F24: =D21*2
E25: Administrative Charge | F25: =D21*1
E26: Access Charges | F26: 0 | K26: =SUM(K23:K25)
